[
  {
    "lng": 118.771835,
    "lat": 32.136169
  },
  {
    "lng": 118.747236,
    "lat": 32.116614
  },
  {
    "lng": 118.730371,
    "lat": 32.094495
  },
  {
    "lng": 118.709619,
    "lat": 32.076258
  },
  {
    "lng": 118.673896,
    "lat": 32.014685
  },
  {
    "lng": 118.671391,
    "lat": 32.004687
  },
  {
    "lng": 118.648926,
    "lat": 31.974899
  },
  {
    "lng": 118.624278,
    "lat": 31.949365
  },
  {
    "lng": 118.602498,
    "lat": 31.932172
  },
  {
    "lng": 118.594064,
    "lat": 31.932849
  },
  {
    "lng": 118.576433,
    "lat": 31.922873
  },
  {
    "lng": 118.530778,
    "lat": 31.8778
  },
  {
    "lng": 118.510011,
    "lat": 31.847442
  },
  {
    "lng": 118.489082,
    "lat": 31.852598
  },
  {
    "lng": 118.474865,
    "lat": 31.862212
  },
  {
    "lng": 118.471996,
    "lat": 31.873443
  },
  {
    "lng": 118.478059,
    "lat": 31.881215
  },
  {
    "lng": 118.477568,
    "lat": 31.885638
  },
  {
    "lng": 118.454442,
    "lat": 31.894473
  },
  {
    "lng": 118.443422,
    "lat": 31.90509
  },
  {
    "lng": 118.431358,
    "lat": 31.904246
  },
  {
    "lng": 118.421168,
    "lat": 31.907546
  },
  {
    "lng": 118.408268,
    "lat": 31.919898
  },
  {
    "lng": 118.39081,
    "lat": 31.916851
  },
  {
    "lng": 118.382003,
    "lat": 31.929969
  },
  {
    "lng": 118.369178,
    "lat": 31.936482
  },
  {
    "lng": 118.374855,
    "lat": 31.949946
  },
  {
    "lng": 118.374364,
    "lat": 31.961918
  },
  {
    "lng": 118.385332,
    "lat": 31.974031
  },
  {
    "lng": 118.381131,
    "lat": 31.986432
  },
  {
    "lng": 118.392529,
    "lat": 31.988938
  },
  {
    "lng": 118.396837,
    "lat": 31.998107
  },
  {
    "lng": 118.394972,
    "lat": 32.017733
  },
  {
    "lng": 118.401141,
    "lat": 32.028092
  },
  {
    "lng": 118.391311,
    "lat": 32.038797
  },
  {
    "lng": 118.393341,
    "lat": 32.047928
  },
  {
    "lng": 118.399654,
    "lat": 32.054728
  },
  {
    "lng": 118.390408,
    "lat": 32.066103
  },
  {
    "lng": 118.399445,
    "lat": 32.070391
  },
  {
    "lng": 118.400122,
    "lat": 32.082107
  },
  {
    "lng": 118.409075,
    "lat": 32.081511
  },
  {
    "lng": 118.409917,
    "lat": 32.085797
  },
  {
    "lng": 118.41705,
    "lat": 32.087453
  },
  {
    "lng": 118.420553,
    "lat": 32.094023
  },
  {
    "lng": 118.437605,
    "lat": 32.093175
  },
  {
    "lng": 118.45498,
    "lat": 32.104784
  },
  {
    "lng": 118.469072,
    "lat": 32.108293
  },
  {
    "lng": 118.477925,
    "lat": 32.115921
  },
  {
    "lng": 118.478807,
    "lat": 32.122651
  },
  {
    "lng": 118.505877,
    "lat": 32.127228
  },
  {
    "lng": 118.500513,
    "lat": 32.1367
  },
  {
    "lng": 118.503766,
    "lat": 32.146846
  },
  {
    "lng": 118.507204,
    "lat": 32.147035
  },
  {
    "lng": 118.511309,
    "lat": 32.141936
  },
  {
    "lng": 118.51291,
    "lat": 32.144865
  },
  {
    "lng": 118.500991,
    "lat": 32.17088
  },
  {
    "lng": 118.500963,
    "lat": 32.182742
  },
  {
    "lng": 118.513745,
    "lat": 32.189961
  },
  {
    "lng": 118.515256,
    "lat": 32.20009
  },
  {
    "lng": 118.52661,
    "lat": 32.194304
  },
  {
    "lng": 118.536493,
    "lat": 32.201631
  },
  {
    "lng": 118.543886,
    "lat": 32.199109
  },
  {
    "lng": 118.55268,
    "lat": 32.201234
  },
  {
    "lng": 118.556905,
    "lat": 32.206587
  },
  {
    "lng": 118.565485,
    "lat": 32.203326
  },
  {
    "lng": 118.578498,
    "lat": 32.208958
  },
  {
    "lng": 118.589025,
    "lat": 32.204249
  },
  {
    "lng": 118.596568,
    "lat": 32.206303
  },
  {
    "lng": 118.599083,
    "lat": 32.20117
  },
  {
    "lng": 118.604315,
    "lat": 32.206462
  },
  {
    "lng": 118.621322,
    "lat": 32.21071
  },
  {
    "lng": 118.634583,
    "lat": 32.208392
  },
  {
    "lng": 118.651171,
    "lat": 32.216896
  },
  {
    "lng": 118.674112,
    "lat": 32.238281
  },
  {
    "lng": 118.680408,
    "lat": 32.256668
  },
  {
    "lng": 118.725422,
    "lat": 32.25601
  },
  {
    "lng": 118.728299,
    "lat": 32.230666
  },
  {
    "lng": 118.737563,
    "lat": 32.222715
  },
  {
    "lng": 118.734209,
    "lat": 32.209923
  },
  {
    "lng": 118.741811,
    "lat": 32.200156
  },
  {
    "lng": 118.739035,
    "lat": 32.1886
  },
  {
    "lng": 118.741958,
    "lat": 32.180044
  },
  {
    "lng": 118.738408,
    "lat": 32.175567
  },
  {
    "lng": 118.755512,
    "lat": 32.190815
  },
  {
    "lng": 118.772924,
    "lat": 32.192367
  },
  {
    "lng": 118.778769,
    "lat": 32.181949
  },
  {
    "lng": 118.782643,
    "lat": 32.157367
  },
  {
    "lng": 118.771835,
    "lat": 32.136169
  }
]